{"stats":{"minecraft:used":{"minecraft:structure_block":2,"wildaside:hanging_vibrion_vines":10,"wildaside:substilium_tree_grower":9,"wildaside:vibrion_gel":23,"wildaside:vibrion_block":59,"wildaside:substilium_block":17,"wildaside:hickory_leaves":18,"wildaside:vibrion_growth":4,"wildaside:lit_vibrion_gel":13,"wildaside:substilium_shroom":112,"wildaside:substilium_stem":18},"minecraft:custom":{"minecraft:time_since_rest":17331,"minecraft:crouch_one_cm":15,"minecraft:play_time":17331,"minecraft:walk_one_cm":17196,"minecraft:sneak_time":874,"minecraft:drop":3,"minecraft:jump":47,"minecraft:leave_game":1,"minecraft:walk_on_water_one_cm":1101,"minecraft:time_since_death":17331,"minecraft:total_world_time":20243,"minecraft:fall_one_cm":269,"minecraft:fly_one_cm":96812},"minecraft:dropped":{"wildaside:vibrion_block":2,"wildaside:hickory_nut":1},"minecraft:picked_up":{"wildaside:hickory_nut":1,"wildaside:hanging_vibrion_vines":3,"wildaside:vibrion_block":3}},"DataVersion":2975}