{"stats":{"minecraft:used":{"wildaside:spore_blaster":2,"minecraft:lever":3,"minecraft:water_bucket":38,"minecraft:lava_bucket":5,"wildaside:hickory_button":11,"wildaside:substilium_planks":8,"wildaside:hickory_fence":15,"minecraft:command_block":1,"wildaside:hickory_log":60,"wildaside:hickory_leaves":87,"minecraft:grass_block":7,"minecraft:redstone":5,"wildaside:substilium_fence":7,"wildaside:substilium_fence_gate":4,"wildaside:hickory_slab":3,"wildaside:substilium_stairs":1,"minecraft:dark_oak_leaves":5,"wildaside:hickory_stairs":3,"wildaside:hickory_pressure_plate":22,"wildaside:stripped_substilium_block":6,"wildaside:hickory_fence_gate":5,"wildaside:stripped_hickory_log":6,"minecraft:oak_leaves":194,"wildaside:substilium_block":9,"minecraft:glow_item_frame":9,"wildaside:substilium_door":3,"wildaside:substilium_button":1,"wildaside:hickory_planks":32,"minecraft:dirt":1,"wildaside:hickory_block":19,"wildaside:substilium_pressure_plate":2,"minecraft:repeating_command_block":2,"wildaside:substilium_stem":4,"wildaside:bioengineer_workspace":2,"wildaside:substilium_slab":4,"wildaside:stripped_hickory_block":2,"wildaside:stripped_substilium_stem":1},"minecraft:picked_up":{"wildaside:hickory_nut":4,"wildaside:hickory_button":1,"minecraft:glow_item_frame":1,"wildaside:hickory_log":1},"minecraft:dropped":{"wildaside:hickory_nut":4,"wildaside:hickory_log":1},"minecraft:custom":{"minecraft:time_since_rest":48386,"minecraft:sprint_one_cm":259,"minecraft:walk_one_cm":43425,"minecraft:drop":5,"minecraft:fly_one_cm":309103,"minecraft:crouch_one_cm":1879,"minecraft:play_time":48386,"minecraft:sneak_time":3038,"minecraft:walk_under_water_one_cm":121,"minecraft:jump":106,"minecraft:leave_game":4,"minecraft:time_since_death":48386,"minecraft:walk_on_water_one_cm":904,"minecraft:total_world_time":295571}},"DataVersion":2975}